{
  "type": "Feature",
  "properties": {
    "gn:admin1_code":"10.0",
    "gn:admin2_code":"90160000.0",
    "gn:asciiname":"Saint Urbain",
    "gn:country_code":"LC",
    "gn:dem":41,
    "gn:feature_class":"P",
    "gn:feature_code":"PPL",
    "gn:name":"Saint Urbain",
    "gn:population":0,
    "gn:timezone":"America/St_Lucia",
    "iso:country":"LC",
    "name:und_x_variant":[
        "Saint Urban",
        "Saint Urbain"
    ],
    "wof:name":"Saint Urbain",
    "wof:placetype":"locality"
},
  "geometry": {"coordinates":[-60.94386,13.76081],"type":"Point"}
}