{
  "type": "Feature",
  "properties": {
    "gn:admin1_code":"10.0",
    "gn:admin2_code":"90230000.0",
    "gn:asciiname":"Cantonement",
    "gn:country_code":"LC",
    "gn:dem":59,
    "gn:feature_class":"P",
    "gn:feature_code":"PPLL",
    "gn:name":"Cantonement",
    "gn:population":0,
    "gn:timezone":"America/St_Lucia",
    "iso:country":"LC",
    "wof:name":"Cantonement",
    "wof:placetype":"locality"
},
  "geometry": {"coordinates":[-60.97529,13.75263],"type":"Point"}
}