{
  "type": "Feature",
  "properties": {
    "gn:admin1_code":"7.0",
    "gn:admin2_code":"80050000.0",
    "gn:asciiname":"Banse",
    "gn:country_code":"LC",
    "gn:dem":209,
    "gn:feature_class":"P",
    "gn:feature_code":"PPL",
    "gn:name":"Banse",
    "gn:population":0,
    "gn:timezone":"America/St_Lucia",
    "iso:country":"LC",
    "wof:name":"Banse",
    "wof:placetype":"locality"
},
  "geometry": {"coordinates":[-60.99493,13.78372],"type":"Point"}
}