{
  "type": "Feature",
  "properties": {
    "gn:admin1_code":"8.0",
    "gn:admin2_code":"100030000.0",
    "gn:asciiname":"Anse Ger",
    "gn:country_code":"LC",
    "gn:dem":64,
    "gn:feature_class":"P",
    "gn:feature_code":"PPL",
    "gn:name":"Anse Ger",
    "gn:population":0,
    "gn:timezone":"America/St_Lucia",
    "iso:country":"LC",
    "wof:name":"Anse Ger",
    "wof:placetype":"locality"
},
  "geometry": {"coordinates":[-60.9164,13.79775],"type":"Point"}
}