{
  "type": "Feature",
  "properties": {
    "gn:admin1_code":"3.0",
    "gn:admin2_code":"30110000.0",
    "gn:asciiname":"Bexon",
    "gn:country_code":"LC",
    "gn:dem":37,
    "gn:feature_class":"P",
    "gn:feature_code":"PPL",
    "gn:name":"Bexon",
    "gn:population":0,
    "gn:timezone":"America/St_Lucia",
    "iso:country":"LC",
    "name:cym_x_preferred":[
        "Bexon"
    ],
    "name:pol_x_preferred":[
        "Bexon"
    ],
    "wof:name":"Bexon",
    "wof:placetype":"locality"
},
  "geometry": {"coordinates":[-60.97782,13.95256],"type":"Point"}
}