{
  "type": "Feature",
  "properties": {
    "gn:admin1_code":"8.0",
    "gn:admin2_code":"100120000.0",
    "gn:asciiname":"Angere",
    "gn:country_code":"LC",
    "gn:dem":13,
    "gn:feature_class":"P",
    "gn:feature_code":"PPL",
    "gn:name":"Angere",
    "gn:population":0,
    "gn:timezone":"America/St_Lucia",
    "iso:country":"LC",
    "wof:name":"Angere",
    "wof:placetype":"locality"
},
  "geometry": {"coordinates":[-60.91667,13.78333],"type":"Point"}
}