{
  "type": "Feature",
  "properties": {
    "gn:admin1_code":"3.0",
    "gn:asciiname":"La Point",
    "gn:cc2":"LC",
    "gn:country_code":"LC",
    "gn:dem":2,
    "gn:feature_class":"P",
    "gn:feature_code":"PPL",
    "gn:name":"La Point",
    "gn:population":0,
    "gn:timezone":"America/St_Lucia",
    "iso:country":"LC",
    "name:und_x_variant":[
        "La Pointe",
        "La Point"
    ],
    "wof:name":"La Point",
    "wof:placetype":"locality"
},
  "geometry": {"coordinates":[-61.03333000000001,13.98333],"type":"Point"}
}