{
  "type": "Feature",
  "properties": {
    "gn:admin1_code":"6.0",
    "gn:admin2_code":"120190000.0",
    "gn:asciiname":"Desbarra",
    "gn:country_code":"LC",
    "gn:dem":253,
    "gn:feature_class":"P",
    "gn:feature_code":"PPL",
    "gn:name":"Desbarra",
    "gn:population":0,
    "gn:timezone":"America/St_Lucia",
    "iso:country":"LC",
    "wof:name":"Desbarra",
    "wof:placetype":"locality"
},
  "geometry": {"coordinates":[-60.90897,13.99345],"type":"Point"}
}