{
  "type": "Feature",
  "properties": {
    "gn:admin1_code":"9.0",
    "gn:admin2_code":"60500000.0",
    "gn:asciiname":"Union Vale",
    "gn:country_code":"LC",
    "gn:dem":232,
    "gn:feature_class":"P",
    "gn:feature_code":"PPL",
    "gn:name":"Union Vale",
    "gn:population":0,
    "gn:timezone":"America/St_Lucia",
    "iso:country":"LC",
    "wof:name":"Union Vale",
    "wof:placetype":"locality"
},
  "geometry": {"coordinates":[-61.05609000000001,13.81119],"type":"Point"}
}