{
  "type": "Feature",
  "properties": {
    "gn:country":"LC",
    "gn:fcode":"PPL",
    "gn:pop":701,
    "iso:country":"LC",
    "name:ara_x_preferred":[
        "\u062c\u0632\u0631 \u0627\u0644\u0643\u0646\u0627\u0631\u064a"
    ],
    "name:ben_x_preferred":[
        "\u0995\u09be\u09a8\u09be\u09b0\u09be\u0987\u09b8\u09c7"
    ],
    "name:ceb_x_preferred":[
        "Canaries"
    ],
    "name:dan_x_preferred":[
        "Canaries"
    ],
    "name:deu_x_preferred":[
        "Canaries"
    ],
    "name:ell_x_preferred":[
        "\u039a\u03b1\u03bd\u03ac\u03c1\u03b9\u03b5\u03c2"
    ],
    "name:eng_x_preferred":[
        "Canaries"
    ],
    "name:epo_x_preferred":[
        "Canaries"
    ],
    "name:eus_x_preferred":[
        "Canaries auzoa"
    ],
    "name:fin_x_preferred":[
        "Canaries"
    ],
    "name:fra_x_preferred":[
        "Canaries"
    ],
    "name:guj_x_preferred":[
        "\u0a95\u0ac7\u0aa8\u0abe\u0ab0\u0ac0\u0ab8"
    ],
    "name:hin_x_preferred":[
        "\u0915\u0948\u0928\u0947\u0930\u0940\u091c\u093c"
    ],
    "name:ind_x_preferred":[
        "Canaries"
    ],
    "name:ita_x_preferred":[
        "Canarie"
    ],
    "name:jpn_x_preferred":[
        "\u30ab\u30ca\u30ea\u30a2\u30b9"
    ],
    "name:kan_x_preferred":[
        "\u0c95\u0ccd\u0caf\u0cbe\u0ca8\u0cb0\u0cc0\u0cb8\u0ccd"
    ],
    "name:kor_x_preferred":[
        "\uce74\ub098\ub9ac\uc544"
    ],
    "name:lav_x_preferred":[
        "Kanarisa"
    ],
    "name:lit_x_preferred":[
        "Kanaris"
    ],
    "name:mar_x_preferred":[
        "\u0915\u0945\u0928\u0947\u0930\u0940\u0938"
    ],
    "name:msa_x_preferred":[
        "Canaries"
    ],
    "name:nld_x_preferred":[
        "Canaries"
    ],
    "name:nob_x_preferred":[
        "Kanariene"
    ],
    "name:pol_x_preferred":[
        "Canaries"
    ],
    "name:por_x_preferred":[
        "Canaries"
    ],
    "name:rus_x_preferred":[
        "\u041a\u0430\u043d\u0430\u0440\u0438\u0441"
    ],
    "name:sin_x_preferred":[
        "\u0d9a\u0dd0\u0db1\u0dbb\u0dd2\u0dc3\u0dca"
    ],
    "name:spa_x_preferred":[
        "Canaries"
    ],
    "name:swe_x_preferred":[
        "Canaries"
    ],
    "name:tam_x_preferred":[
        "\u0b95\u0bbe\u0ba9\u0bb0\u0bbf\u0bb8\u0bcd"
    ],
    "name:tel_x_preferred":[
        "\u0c15\u0c47\u0c28\u0c30\u0c40\u0c38\u0c4d"
    ],
    "name:tha_x_preferred":[
        "\u0e04\u0e32\u0e19\u0e32\u0e23\u0e35\u0e48 \u0e40\u0e0b\u0e19\u0e15\u0e4c \u0e25\u0e39\u0e40\u0e0b\u0e35\u0e22"
    ],
    "name:tur_x_preferred":[
        "Canaries"
    ],
    "name:ukr_x_preferred":[
        "\u041a\u0430\u043d\u0430\u0440\u0456\u0441"
    ],
    "name:unk_x_variant":[
        "Two Friends"
    ],
    "name:urd_x_preferred":[
        "\u06a9\u0646\u0627\u0631\u06cc\u0632\u060c \u0633\u06cc\u0646\u0679 \u0644\u0648\u0633\u06cc\u0627"
    ],
    "name:urd_x_variant":[
        "\u06a9\u0646\u0627\u0631\u06cc\u0632"
    ],
    "name:vie_x_preferred":[
        "Canaries"
    ],
    "name:zho_x_preferred":[
        "\u5361\u7d0d\u91cc\u65af"
    ],
    "qs:name":"Canaries",
    "qs:photos_9r":0,
    "qs:photos_sr":0,
    "qs:pop_sr":"2",
    "wd:wordcount":88,
    "wof:name":"Canaries",
    "wof:placetype":"locality",
    "wof:population":701
},
  "geometry": {"coordinates":[-61.06459,13.90224],"type":"Point"}
}