{
  "type": "Feature",
  "properties": {
    "gn:admin1_code":"5.0",
    "gn:admin2_code":"110370000.0",
    "gn:asciiname":"Riche Fond",
    "gn:country_code":"LC",
    "gn:dem":17,
    "gn:feature_class":"P",
    "gn:feature_code":"PPL",
    "gn:name":"Riche Fond",
    "gn:population":0,
    "gn:timezone":"America/St_Lucia",
    "iso:country":"LC",
    "wof:name":"Riche Fond",
    "wof:placetype":"locality"
},
  "geometry": {"coordinates":[-60.92055,13.93649],"type":"Point"}
}