{
  "type": "Feature",
  "properties": {
    "gn:admin1_code":"6.0",
    "gn:admin2_code":"120330700.0",
    "gn:asciiname":"La Feuillet",
    "gn:country_code":"LC",
    "gn:dem":43,
    "gn:feature_class":"P",
    "gn:feature_code":"PPLL",
    "gn:name":"La Feuillet",
    "gn:population":0,
    "gn:timezone":"America/St_Lucia",
    "iso:country":"LC",
    "wof:name":"La Feuillet",
    "wof:placetype":"locality"
},
  "geometry": {"coordinates":[-60.93824,14.05133],"type":"Point"}
}