{
  "type": "Feature",
  "properties": {
    "gn:admin1_code":"3.0",
    "gn:admin2_code":"30050000.0",
    "gn:asciiname":"Balata",
    "gn:country_code":"LC",
    "gn:dem":37,
    "gn:feature_class":"P",
    "gn:feature_code":"PPL",
    "gn:name":"Balata",
    "gn:population":0,
    "gn:timezone":"America/St_Lucia",
    "iso:country":"LC",
    "name:ara_x_preferred":[
        "\u0645\u062e\u064a\u0645 \u0628\u0644\u0627\u0637\u0629"
    ],
    "name:cat_x_preferred":[
        "Balata"
    ],
    "name:ceb_x_preferred":[
        "Bal\u0101\u0163ah"
    ],
    "name:epo_x_preferred":[
        "Balata"
    ],
    "name:fas_x_preferred":[
        "\u0627\u0631\u062f\u0648\u06af\u0627\u0647 \u0628\u0644\u0627\u0637\u0647"
    ],
    "name:fra_x_preferred":[
        "Balata"
    ],
    "name:heb_x_preferred":[
        "\u05d1\u05dc\u05d0\u05d8\u05d4"
    ],
    "name:pol_x_preferred":[
        "Muchajjam Balata"
    ],
    "name:rus_x_preferred":[
        "\u0411\u0430\u043b\u0430\u0442\u0430"
    ],
    "wof:name":"Balata",
    "wof:placetype":"locality"
},
  "geometry": {"coordinates":[-60.95598,14.01397],"type":"Point"}
}