{
  "type": "Feature",
  "properties": {
    "gn:admin1_code":"3.0",
    "gn:admin2_code":"30050000.0",
    "gn:asciiname":"Balata",
    "gn:country_code":"LC",
    "gn:dem":37,
    "gn:feature_class":"P",
    "gn:feature_code":"PPL",
    "gn:name":"Balata",
    "gn:population":0,
    "gn:timezone":"America/St_Lucia",
    "iso:country":"LC",
    "wof:name":"Balata",
    "wof:placetype":"locality"
},
  "geometry": {"coordinates":[-60.95598,14.01397],"type":"Point"}
}