{
  "type": "Feature",
  "properties": {
    "gn:admin1_code":"7.0",
    "gn:admin2_code":"80160000.0",
    "gn:asciiname":"H'Erelle",
    "gn:country_code":"LC",
    "gn:dem":60,
    "gn:feature_class":"P",
    "gn:feature_code":"PPL",
    "gn:name":"H\u2019Erelle",
    "gn:population":0,
    "gn:timezone":"America/St_Lucia",
    "iso:country":"LC",
    "wof:name":"H'Erelle",
    "wof:placetype":"locality"
},
  "geometry": {"coordinates":[-60.98824000000001,13.75651],"type":"Point"}
}