{
  "type": "Feature",
  "properties": {
    "gn:admin1_code":"3.0",
    "gn:admin2_code":"20820000.0",
    "gn:asciiname":"Charlotte",
    "gn:country_code":"LC",
    "gn:dem":222,
    "gn:feature_class":"P",
    "gn:feature_code":"PPL",
    "gn:name":"Charlotte",
    "gn:population":0,
    "gn:timezone":"America/St_Lucia",
    "iso:country":"LC",
    "name:und_x_variant":[
        "Charlotre",
        "Charlotte"
    ],
    "wof:name":"Charlotte",
    "wof:placetype":"locality"
},
  "geometry": {"coordinates":[-60.9965,14.00076],"type":"Point"}
}