{
  "type": "Feature",
  "properties": {
    "gn:admin1_code":"9.0",
    "gn:admin2_code":"60130000.0",
    "gn:asciiname":"Colombette",
    "gn:country_code":"LC",
    "gn:dem":354,
    "gn:feature_class":"P",
    "gn:feature_code":"PPL",
    "gn:name":"Colombette",
    "gn:population":0,
    "gn:timezone":"America/St_Lucia",
    "iso:country":"LC",
    "wof:name":"Colombette",
    "wof:placetype":"locality"
},
  "geometry": {"coordinates":[-61.05474,13.86643],"type":"Point"}
}