{
  "type": "Feature",
  "properties": {
    "gn:admin1_code":"6.0",
    "gn:admin2_code":"120290100.0",
    "gn:asciiname":"Bon Air",
    "gn:country_code":"LC",
    "gn:dem":33,
    "gn:feature_class":"P",
    "gn:feature_code":"PPL",
    "gn:name":"Bon Air",
    "gn:population":0,
    "gn:timezone":"America/St_Lucia",
    "iso:country":"LC",
    "name:ceb_x_preferred":[
        "Bon Air"
    ],
    "name:deu_x_preferred":[
        "Bon Air"
    ],
    "name:ido_x_preferred":[
        "Bon Air"
    ],
    "name:ita_x_preferred":[
        "Bon Air"
    ],
    "name:nld_x_preferred":[
        "Bon Air"
    ],
    "name:por_x_preferred":[
        "Bon Air"
    ],
    "name:spa_x_preferred":[
        "Bon Air"
    ],
    "name:srp_x_preferred":[
        "\u0411\u043e\u043d \u0415\u0440"
    ],
    "name:ukr_x_preferred":[
        "\u0411\u043e\u043d-\u0415\u0439\u0440"
    ],
    "name:vol_x_preferred":[
        "Bon Air"
    ],
    "wof:name":"Bon Air",
    "wof:placetype":"locality"
},
  "geometry": {"coordinates":[-60.9695,14.04845],"type":"Point"}
}