{
  "type": "Feature",
  "properties": {
    "gn:admin1_code":"10.0",
    "gn:admin2_code":"90260000.0",
    "gn:asciiname":"La Resource",
    "gn:country_code":"LC",
    "gn:dem":24,
    "gn:feature_class":"P",
    "gn:feature_code":"PPL",
    "gn:name":"La Resource",
    "gn:population":0,
    "gn:timezone":"America/St_Lucia",
    "iso:country":"LC",
    "name:und_x_variant":[
        "Ressource",
        "La Resource"
    ],
    "wof:name":"La Resource",
    "wof:placetype":"locality"
},
  "geometry": {"coordinates":[-60.95841,13.7457],"type":"Point"}
}