{
  "type": "Feature",
  "properties": {
    "gn:admin1_code":"8.0",
    "gn:admin2_code":"100430000.0",
    "gn:asciiname":"Patience",
    "gn:country_code":"LC",
    "gn:dem":115,
    "gn:feature_class":"P",
    "gn:feature_code":"PPL",
    "gn:name":"Patience",
    "gn:population":0,
    "gn:timezone":"America/St_Lucia",
    "iso:country":"LC",
    "name:ara_x_preferred":[
        "\u0635\u0628\u0631"
    ],
    "name:bod_x_preferred":[
        "\u0f56\u0f5f\u0f7c\u0f51\u0f0b\u0f54\u0f0d"
    ],
    "name:bul_x_preferred":[
        "\u0422\u044a\u0440\u043f\u0435\u043d\u0438\u0435"
    ],
    "name:cat_x_preferred":[
        "Paci\u00e8ncia"
    ],
    "name:ces_x_preferred":[
        "M\u00edrumilovnost"
    ],
    "name:deu_x_preferred":[
        "Geduld"
    ],
    "name:eml_x_preferred":[
        "Pas\u00ecnsia"
    ],
    "name:epo_x_preferred":[
        "Pacienco"
    ],
    "name:eus_x_preferred":[
        "Pazientzia"
    ],
    "name:fas_x_preferred":[
        "\u0634\u06a9\u06cc\u0628\u0627\u06cc\u06cc"
    ],
    "name:fra_x_preferred":[
        "Patience"
    ],
    "name:gle_x_preferred":[
        "Foighne"
    ],
    "name:grn_x_preferred":[
        "Jahei'\u1ef9"
    ],
    "name:heb_x_preferred":[
        "\u05e1\u05d1\u05dc\u05e0\u05d5\u05ea"
    ],
    "name:hin_x_preferred":[
        "\u0927\u0948\u0930\u094d\u092f"
    ],
    "name:ina_x_preferred":[
        "Patientia"
    ],
    "name:ind_x_preferred":[
        "Sabar"
    ],
    "name:ita_x_preferred":[
        "Pazienza"
    ],
    "name:kan_x_preferred":[
        "\u0ca4\u0cbe\u0cb3\u0ccd\u0cae\u0cc6"
    ],
    "name:mya_x_preferred":[
        "\u101e\u100a\u103a\u1038\u1001\u1036\u1001\u103c\u1004\u103a\u1038"
    ],
    "name:new_x_preferred":[
        "\u0927\u0948\u0930\u094d\u092f"
    ],
    "name:nld_x_preferred":[
        "Geduld"
    ],
    "name:por_x_preferred":[
        "Paci\u00eancia"
    ],
    "name:rus_x_preferred":[
        "\u0422\u0435\u0440\u043f\u0435\u043d\u0438\u0435"
    ],
    "name:slk_x_preferred":[
        "Mierumilovnos\u0165"
    ],
    "name:snd_x_preferred":[
        "\u0635\u0628\u0631"
    ],
    "name:spa_x_preferred":[
        "Paciencia"
    ],
    "name:sqi_x_preferred":[
        "Durimi"
    ],
    "name:swe_x_preferred":[
        "T\u00e5lamod"
    ],
    "name:tam_x_preferred":[
        "\u0baa\u0bca\u0bb1\u0bc1\u0bae\u0bc8"
    ],
    "name:tel_x_preferred":[
        "\u0c38\u0c39\u0c28\u0c02"
    ],
    "name:tgl_x_preferred":[
        "Tiyaga"
    ],
    "name:tur_x_preferred":[
        "Sab\u0131r"
    ],
    "name:ukr_x_preferred":[
        "\u0422\u0435\u0440\u043f\u0435\u043b\u0438\u0432\u0456\u0441\u0442\u044c"
    ],
    "name:uzb_x_preferred":[
        "Sabr"
    ],
    "name:vie_x_preferred":[
        "Ki\u00ean nh\u1eabn"
    ],
    "name:yid_x_preferred":[
        "\u05d2\u05e2\u05d3\u05d5\u05dc\u05d3"
    ],
    "wof:name":"Patience",
    "wof:placetype":"locality"
},
  "geometry": {"coordinates":[-60.90949000000001,13.85114],"type":"Point"}
}