{
  "type": "Feature",
  "properties": {
    "gn:admin1_code":"8.0",
    "gn:admin2_code":"100430000.0",
    "gn:asciiname":"Patience",
    "gn:country_code":"LC",
    "gn:dem":115,
    "gn:feature_class":"P",
    "gn:feature_code":"PPL",
    "gn:name":"Patience",
    "gn:population":0,
    "gn:timezone":"America/St_Lucia",
    "iso:country":"LC",
    "wof:name":"Patience",
    "wof:placetype":"locality"
},
  "geometry": {"coordinates":[-60.90949000000001,13.85114],"type":"Point"}
}