{
  "type": "Feature",
  "properties": {
    "iso:country":"LC",
    "name:deu_x_preferred":[
        "Anse-la-Raye"
    ],
    "name:ell_x_preferred":[
        "\u0391\u03bd\u03c2 \u03bb\u03b1 \u03a1\u03ac\u03b9\u03b3"
    ],
    "name:eng_x_preferred":[
        "Anse La Raye"
    ],
    "name:fra_x_preferred":[
        "Anse-la-Raye"
    ],
    "name:nld_x_preferred":[
        "Anse La Raye"
    ],
    "name:pol_x_preferred":[
        "Anse la Raye"
    ],
    "name:spa_x_preferred":[
        "Anse La Raye"
    ],
    "name:swe_x_preferred":[
        "Anse La Raye"
    ],
    "name:unk_x_variant":[
        "La Raye"
    ],
    "qs:gn_pop":0,
    "qs:name":"Anse la Raye",
    "qs:name_adm0":"St. Lucia",
    "qs:name_adm1":"Ansela-Raye",
    "qs:photos":3108,
    "qs:photos_1k":630,
    "qs:photos_9k":14,
    "qs:photos_9r":11,
    "qs:photos_all":3108,
    "qs:photos_sr":20,
    "qs:placetype":"Town",
    "qs:pop_sr":"0",
    "qs:woe_adm0":23424951,
    "wof:name":"Anse la Raye",
    "wof:placetype":"locality"
},
  "geometry": {"coordinates":[-61.041412,13.931734],"type":"Point"}
}