{
  "type": "Feature",
  "properties": {
    "gn:admin1_code":"4.0",
    "gn:admin2_code":"70080000.0",
    "gn:asciiname":"Debreuil",
    "gn:country_code":"LC",
    "gn:dem":190,
    "gn:feature_class":"P",
    "gn:feature_code":"PPL",
    "gn:name":"Debreuil",
    "gn:population":0,
    "gn:timezone":"America/St_Lucia",
    "iso:country":"LC",
    "wof:name":"Debreuil",
    "wof:placetype":"locality"
},
  "geometry": {"coordinates":[-61.02855,13.78822],"type":"Point"}
}